tests/__init__.py
tests/test_things_cli.py
things_cli/__init__.py
things_cli/cli.py
things_cli-0.0.5.dist-info/METADATA
things_cli-0.0.5.dist-info/WHEEL
things_cli-0.0.5.dist-info/entry_points.txt
things_cli-0.0.5.dist-info/top_level.txt
things_cli-0.0.5.dist-info/RECORD
