Metadata-Version: 2.1
Name: things-cli
Version: 0.0.5
Summary: A simple Python 3 CLI to read your Things app data.
Home-page: https://github.com/thingsapi/things-cli
Author: Alexander Willner
Author-email: alex@willner.ws
License: UNKNOWN
Platform: UNKNOWN
Classifier: Development Status :: 4 - Beta
Classifier: Programming Language :: Python :: 3
Classifier: License :: OSI Approved :: Apache Software License
Classifier: Operating System :: MacOS :: MacOS X
Classifier: Natural Language :: English
Requires-Python: >=3.6
Requires-Dist: things.py
Requires-Dist: argcomplete
